{"name":"health","slug":"health","path":"/tags/health.json","posts":[{"title":"June 2019 update","slug":"june-2019-update","path":"/posts/june-2019-update/june-2019-update.json","date":"2019-06-19T01:42:16Z","excerpt":"This month I'm working on my blog and publishing pipeline. I'm looking for contract programming work. I'm experimenting with Oura ring to improve my sleep and I'm trying to live healthier.","tags":[{"name":"now","slug":"now","path":"/tags/now.json"},{"name":"Oura ring","slug":"oura-ring","path":"/tags/oura-ring.json"},{"name":"health","slug":"health","path":"/tags/health.json"},{"name":"my blog engine","slug":"my-blog-engine","path":"/tags/my-blog-engine.json"},{"name":"OSS","slug":"oss","path":"/tags/oss.json"}]}]}
